{
  "metadata": {
    "id": "2022-rmpa-show-2-virtual-february-26",
    "eventName": "RMPA Show #2 - Virtual",
    "venue": "",
    "date": "Saturday, February 26, 2022",
    "round": "",
    "year": 2022
  },
  "classes": [
    {
      "classDef": {
        "id": "percussion-scholastic-concert-regional-a",
        "name": "Percussion Scholastic Concert Regional A",
        "classType": "concert"
      },
      "ensembles": [
        {
          "ensembleName": "Englewood High School",
          "location": "Englewood , Colorado",
          "captions": [
            {
              "captionName": "Judge",
              "judges": [
                {
                  "judgeName": "M. Nevin",
                  "subCaptions": [
                    {
                      "key": "IMP",
                      "rawScore": 72,
                      "rank": null
                    },
                    {
                      "key": "AN",
                      "rawScore": 68,
                      "rank": null
                    }
                  ],
                  "total": 35,
                  "rank": null
                },
                {
                  "judgeName": "W. Durrett",
                  "subCaptions": [
                    {
                      "key": "IMP",
                      "rawScore": 67,
                      "rank": null
                    },
                    {
                      "key": "AN",
                      "rawScore": 61,
                      "rank": null
                    }
                  ],
                  "total": 32,
                  "rank": null
                }
              ],
              "captionTotal": 0,
              "captionRank": null
            }
          ],
          "subTotal": 32,
          "penalty": 0,
          "total": 0,
          "rank": 0
        }
      ]
    },
    {
      "classDef": {
        "id": "percussion-scholastic-standstill-a",
        "name": "Percussion Scholastic Standstill A",
        "classType": "standstill"
      },
      "ensembles": [
        {
          "ensembleName": "Mesa Ridge Percussion Ensemble",
          "location": "Colorado Springs, CO",
          "captions": [
            {
              "captionName": "Judge",
              "judges": [
                {
                  "judgeName": "M. Nevin",
                  "subCaptions": [
                    {
                      "key": "IMP",
                      "rawScore": 62,
                      "rank": null
                    },
                    {
                      "key": "AN",
                      "rawScore": 65,
                      "rank": null
                    }
                  ],
                  "total": 31.75,
                  "rank": null
                },
                {
                  "judgeName": "W. Durrett",
                  "subCaptions": [
                    {
                      "key": "IMP",
                      "rawScore": 76,
                      "rank": null
                    },
                    {
                      "key": "AN",
                      "rawScore": 75,
                      "rank": null
                    }
                  ],
                  "total": 37.75,
                  "rank": null
                }
              ],
              "captionTotal": 0,
              "captionRank": null
            }
          ],
          "subTotal": 37.75,
          "penalty": 0,
          "total": 0,
          "rank": 0
        }
      ]
    },
    {
      "classDef": {
        "id": "percussion-scholastic-concert-open",
        "name": "Percussion Scholastic Concert Open",
        "classType": "concert"
      },
      "ensembles": [
        {
          "ensembleName": "Heritage High School",
          "location": "Highlands Ranch, Colorado",
          "captions": [
            {
              "captionName": "Judge",
              "judges": [
                {
                  "judgeName": "M. Nevin",
                  "subCaptions": [
                    {
                      "key": "IMP",
                      "rawScore": 75,
                      "rank": null
                    },
                    {
                      "key": "AN",
                      "rawScore": 68,
                      "rank": null
                    }
                  ],
                  "total": 35.75,
                  "rank": null
                },
                {
                  "judgeName": "W. Durrett",
                  "subCaptions": [
                    {
                      "key": "IMP",
                      "rawScore": 66,
                      "rank": null
                    },
                    {
                      "key": "AN",
                      "rawScore": 64,
                      "rank": null
                    }
                  ],
                  "total": 32.5,
                  "rank": null
                }
              ],
              "captionTotal": 0,
              "captionRank": null
            }
          ],
          "subTotal": 32.5,
          "penalty": 0,
          "total": 0,
          "rank": 0
        }
      ]
    }
  ]
}